py_strongly_typed/__init__.py
py_strongly_typed/contracts.py
py_strongly_typed/decorators.py
py_strongly_typed/exceptions.py
py_strongly_typed/typed_class.py
py_strongly_typed/utils.py
py_strongly_typed/use_cases/__init__.py
py_strongly_typed/use_cases/validate_annotations_use_case.py
py_strongly_typed-2.0.0.dist-info/LICENSE
py_strongly_typed-2.0.0.dist-info/METADATA
py_strongly_typed-2.0.0.dist-info/WHEEL
py_strongly_typed-2.0.0.dist-info/top_level.txt
py_strongly_typed-2.0.0.dist-info/RECORD
