Metadata-Version: 2.1
Name: py-strongly-typed
Version: 2.0.0
Summary: Python type enforcer
Author: Christian Silva
Author-email: chrislcontrol@hotmail.com
License: MIT License
Project-URL: GitHub, https://github.com/chrislcontrol/py-strongly-typed
Project-URL: Tracker, https://github.com/chrislcontrol/py-strongly-typed/issues
Requires-Python: >=3.5
License-File: LICENSE
Requires-Dist: wheel
Provides-Extra: dev
Requires-Dist: pycodestyle ; extra == 'dev'
Requires-Dist: flake8 ; extra == 'dev'
Requires-Dist: twine (>=4.0.2) ; extra == 'dev'
